{
  "q1": {
    "q": "запитати",
    "a1": "ask",
    "a2": "answer",
    "a3": "reply",
    "a4": "tell",
    "c": "ask"
  },
  "q2": {
    "q": "заснув",
    "a1": "fallen asleep",
    "a2": "sung",
    "a3": "built",
    "a4": "eaten",
    "c": "built"
  },
  "q3": {
    "q": "дупою",
    "a1": "with the foot",
    "a2": "by the way",
    "a3": "with the elbow",
    "a4": "with the hand",
    "c": "with the foot"
  },
  "q4": {
    "q": "за адресою",
    "a1": "at the address",
    "a2": "under the tree",
    "a3": "behind the house",
    "a4": "in the park",
    "c": "at the address"
  },
  "q5": {
    "q": "атака",
    "a1": "retreat",
    "a2": "surrender",
    "a3": "defense",
    "a4": "attack",
    "c": "attack"
  },
  "q6": {
    "q": "спроба",
    "a1": "regret",
    "a2": "attempt",
    "a3": "failure",
    "a4": "success",
    "c": "attempt"
  },
  "q7": {
    "q": "увага",
    "a1": "ignorance",
    "a2": "attention",
    "a3": "negligence",
    "a4": "disinterest",
    "c": "attention"
  },
  "q8": {
    "q": "тітка",
    "a1": "grandmother",
    "a2": "aunt",
    "a3": "mother",
    "a4": "sister",
    "c": "aunt"
  },
  "q9": {
    "q": "уникати",
    "a1": "to ignore",
    "a2": "to avoid",
    "a3": "to confront",
    "a4": "to welcome",
    "c": "to avoid"
  },
  "q10": {
    "q": "геть",
    "a1": "sit down",
    "a2": "stand still",
    "a3": "go away",
    "a4": "come here",
    "c": "go away"
  },
  "q11": {
    "q": "назад",
    "a1": "back",
    "a2": "up",
    "a3": "forward",
    "a4": "down",
    "c": "back"
  },
  "q12": {
    "q": "поганий",
    "a1": "happy",
    "a2": "poor",
    "a3": "quiet",
    "a4": "tall",
    "c": "poor"
  },
  "q13": {
    "q": "мішок",
    "a1": "dog",
    "a2": "tree",
    "a3": "car",
    "a4": "bag",
    "c": "bag"
  },
  "q14": {
    "q": "м'яч",
    "a1": "shoe",
    "a2": "pencil",
    "a3": "book",
    "a4": "ball",
    "c": "ball"
  },
  "q15": {
    "q": "група",
    "a1": "team",
    "a2": "group",
    "a3": "family",
    "a4": "class",
    "c": "group"
  },
  "q16": {
    "q": "бар",
    "a1": "store",
    "a2": "bar",
    "a3": "library",
    "a4": "restaurant",
    "c": "bar"
  },
  "q17": {
    "q": "ледве",
    "a1": "loudly",
    "a2": "always",
    "a3": "barely",
    "a4": "quickly",
    "c": "barely"
  },
  "q18": {
    "q": "ванна кімната",
    "a1": "bathroom",
    "a2": "bedroom",
    "a3": "living room",
    "a4": "kitchen",
    "c": "bathroom"
  },
  "q19": {
    "q": "бити",
    "a1": "play",
    "a2": "beat",
    "a3": "dance",
    "a4": "sing",
    "c": "beat"
  },
  "q20": {
    "q": "став",
    "a1": "stood",
    "a2": "went",
    "a3": "sat",
    "a4": "came",
    "c": "stood"
  },
  "q21": {
    "q": "тому що",
    "a1": "because",
    "a2": "although",
    "a3": "however",
    "a4": "even though",
    "c": "because"
  },
  "q22": {
    "q": "стають",
    "a1": "bend",
    "a2": "buy",
    "a3": "become",
    "a4": "bet",
    "c": "become"
  },
  "q23": {
    "q": "був",
    "a1": "is",
    "a2": "am",
    "a3": "was",
    "a4": "be",
    "c": "was"
  },
  "q24": {
    "q": "до того, як",
    "a1": "since",
    "a2": "after",
    "a3": "before",
    "a4": "during",
    "c": "before"
  },
  "q25": {
    "q": "почалося",
    "a1": "ended",
    "a2": "started",
    "a3": "paused",
    "a4": "continued",
    "c": "started"
  },
  "q26": {
    "q": "починається",
    "a1": "resumes",
    "a2": "begins",
    "a3": "pauses",
    "a4": "finishes",
    "c": "begins"
  },
  "q27": {
    "q": "позаду",
    "a1": "above",
    "a2": "below",
    "a3": "behind",
    "a4": "ahead",
    "c": "behind"
  },
  "q28": {
    "q": "поруч з",
    "a1": "inside",
    "a2": "near",
    "a3": "outside",
    "a4": "far from",
    "c": "near"
  },
  "q29": {
    "q": "Крім того",
    "a1": "in addition",
    "a2": "however",
    "a3": "meanwhile",
    "a4": "nevertheless",
    "c": "in addition"
  },
  "q30": {
    "q": "між",
    "a1": "inside",
    "a2": "outside",
    "a3": "among",
    "a4": "around",
    "c": "among"
  },
  "q31": {
    "q": "великий",
    "a1": "small",
    "a2": "tall",
    "a3": "big",
    "a4": "short",
    "c": "big"
  },
  "q32": {
    "q": "трохи",
    "a1": "much",
    "a2": "little",
    "a3": "fast",
    "a4": "big",
    "c": "little"
  },
  "q33": {
    "q": "укус",
    "a1": "push",
    "a2": "scratch",
    "a3": "sting",
    "a4": "pull",
    "c": "sting"
  },
  "q34": {
    "q": "моргнути",
    "a1": "smile",
    "a2": "nod",
    "a3": "laugh",
    "a4": "wink",
    "c": "wink"
  },
  "q35": {
    "q": "блок",
    "a1": "block",
    "a2": "short",
    "a3": "round",
    "a4": "red",
    "c": "block"
  },
  "q36": {
    "q": "рум'янець",
    "a1": "grin",
    "a2": "frown",
    "a3": "smirk",
    "a4": "blush",
    "c": "blush"
  },
  "q37": {
    "q": "нудьга",
    "a1": "happiness",
    "a2": "excitement",
    "a3": "boredom",
    "a4": "anxiety",
    "c": "boredom"
  },
  "q38": {
    "q": "обидва",
    "a1": "either",
    "a2": "neither",
    "a3": "both",
    "a4": "none",
    "c": "both"
  },
  "q39": {
    "q": "турбуватися",
    "a1": "worry",
    "a2": "laugh",
    "a3": "relax",
    "a4": "smile",
    "c": "worry"
  },
  "q40": {
    "q": "дно",
    "a1": "middle",
    "a2": "surface",
    "a3": "top",
    "a4": "bottom",
    "c": "bottom"
  },
  "q41": {
    "q": "мозок",
    "a1": "lung",
    "a2": "liver",
    "a3": "brain",
    "a4": "heart",
    "c": "brain"
  },
  "q42": {
    "q": "перерва",
    "a1": "break",
    "a2": "sun",
    "a3": "friend",
    "a4": "hope",
    "c": "break"
  },
  "q43": {
    "q": "дихання",
    "a1": "breathing",
    "a2": "fishing",
    "a3": "swimming",
    "a4": "hunting",
    "c": "breathing"
  },
  "q44": {
    "q": "дихати",
    "a1": "to breathe",
    "a2": "to eat",
    "a3": "to sleep",
    "a4": "to drink",
    "c": "to breathe"
  },
  "q45": {
    "q": "яскравий",
    "a1": "bright",
    "a2": "dull",
    "a3": "grey",
    "a4": "dark",
    "c": "bright"
  },
  "q46": {
    "q": "принести",
    "a1": "to bring",
    "a2": "to lose",
    "a3": "to leave",
    "a4": "to take",
    "c": "to bring"
  },
  "q47": {
    "q": "розбитий",
    "a1": "new",
    "a2": "broken",
    "a3": "fixed",
    "a4": "working",
    "c": "broken"
  },
  "q48": {
    "q": "принесли",
    "a1": "brought",
    "a2": "lost",
    "a3": "left",
    "a4": "taken",
    "c": "brought"
  },
  "q49": {
    "q": "пензлик",
    "a1": "crayon",
    "a2": "paintbrush",
    "a3": "pen",
    "a4": "pencil",
    "c": "paintbrush"
  },
  "q50": {
    "q": "збірка",
    "a1": "bag",
    "a2": "book",
    "a3": "collection",
    "a4": "box",
    "c": "collection"
  },
  "q51": {
    "q": "рум'янець",
    "a1": "smile",
    "a2": "blush",
    "a3": "laugh",
    "a4": "frown",
    "c": "blush"
  },
  "q52": {
    "q": "горіти",
    "a1": "to burn",
    "a2": "to swim",
    "a3": "to sing",
    "a4": "to fly",
    "c": "to burn"
  },
  "q53": {
    "q": "вибух",
    "a1": "explosion",
    "a2": "car",
    "a3": "dog",
    "a4": "house",
    "c": "explosion"
  },
  "q54": {
    "q": "зайнятий",
    "a1": "free",
    "a2": "tall",
    "a3": "busy",
    "a4": "thin",
    "c": "busy"
  },
  "q55": {
    "q": "але",
    "a1": "if",
    "a2": "but",
    "a3": "or",
    "a4": "and",
    "c": "but"
  },
  "q56": {
    "q": "купити",
    "a1": "to sell",
    "a2": "to dance",
    "a3": "to cook",
    "a4": "to buy",
    "c": "to buy"
  },
  "q57": {
    "q": "до",
    "a1": "from",
    "a2": "to",
    "a3": "with",
    "a4": "for",
    "c": "to"
  },
  "q58": {
    "q": "спокій",
    "a1": "peace",
    "a2": "hate",
    "a3": "love",
    "a4": "war",
    "c": "peace"
  },
  "q59": {
    "q": "прийшов",
    "a1": "to go",
    "a2": "to come",
    "a3": "to stay",
    "a4": "to leave",
    "c": "to come"
  },
  "q60": {
    "q": "догляд",
    "a1": "neglect",
    "a2": "trust",
    "a3": "care",
    "a4": "distrust",
    "c": "care"
  },
  "q61": {
    "q": "обережно",
    "a1": "fast",
    "a2": "carefully",
    "a3": "slow",
    "a4": "carelessly",
    "c": "carefully"
  },
  "q62": {
    "q": "нести",
    "a1": "to swim",
    "a2": "to run",
    "a3": "to fly",
    "a4": "to carry",
    "c": "to carry"
  },
  "q63": {
    "q": "випадок",
    "a1": "success",
    "a2": "failure",
    "a3": "victory",
    "a4": "accident",
    "c": "accident"
  },
  "q64": {
    "q": "улов",
    "a1": "catch",
    "a2": "hit",
    "a3": "throw",
    "a4": "kick",
    "c": "catch"
  },
  "q65": {
    "q": "впіймали",
    "a1": "found",
    "a2": "lost",
    "a3": "missed",
    "a4": "caught",
    "c": "caught"
  },
  "q66": {
    "q": "тому що",
    "a1": "because",
    "a2": "however",
    "a3": "therefore",
    "a4": "although",
    "c": "because"
  },
  "q67": {
    "q": "клітина",
    "a1": "cell",
    "a2": "system",
    "a3": "tissue",
    "a4": "organ",
    "c": "cell"
  },
  "q68": {
    "q": "шанс",
    "a1": "chance",
    "a2": "option",
    "a3": "decision",
    "a4": "choice",
    "c": "chance"
  },
  "q69": {
    "q": "зміна",
    "a1": "decrease",
    "a2": "growth",
    "a3": "change",
    "a4": "improvement",
    "c": "change"
  },
  "q70": {
    "q": "гонитва",
    "a1": "fight",
    "a2": "escape",
    "a3": "hide",
    "a4": "chase",
    "c": "chase"
  },
  "q71": {
    "q": "перевірка",
    "a1": "exam",
    "a2": "quiz",
    "a3": "check",
    "a4": "test",
    "c": "check"
  },
  "q72": {
    "q": "щока",
    "a1": "shoulder",
    "a2": "cheek",
    "a3": "elbow",
    "a4": "hip",
    "c": "cheek"
  },
  "q73": {
    "q": "скриня",
    "a1": "desk",
    "a2": "box",
    "a3": "table",
    "a4": "chair",
    "c": "box"
  },
  "q74": {
    "q": "хихикання",
    "a1": "whisper",
    "a2": "scream",
    "a3": "laugh",
    "a4": "cry",
    "c": "laugh"
  },
  "q75": {
    "q": "клас",
    "a1": "grade",
    "a2": "class",
    "a3": "lesson",
    "a4": "teacher",
    "c": "class"
  },
  "q76": {
    "q": "ясно",
    "a1": "clear",
    "a2": "foggy",
    "a3": "unclear",
    "a4": "dark",
    "c": "clear"
  },
  "q77": {
    "q": "підніматися",
    "a1": "to raise",
    "a2": "to twist",
    "a3": "to lower",
    "a4": "to bend",
    "c": "to raise"
  },
  "q78": {
    "q": "близько",
    "a1": "close",
    "a2": "remote",
    "a3": "far",
    "a4": "distant",
    "c": "close"
  },
  "q79": {
    "q": "одяг",
    "a1": "shoes",
    "a2": "house",
    "a3": "food",
    "a4": "clothing",
    "c": "clothing"
  },
  "q80": {
    "q": "коментар",
    "a1": "comment",
    "a2": "exclamation",
    "a3": "answer",
    "a4": "question",
    "c": "comment"
  },
  "q81": {
    "q": "повний",
    "a1": "full",
    "a2": "empty",
    "a3": "complete",
    "a4": "partial",
    "c": "full"
  },
  "q82": {
    "q": "повністю",
    "a1": "mostly",
    "a2": "fully",
    "a3": "partially",
    "a4": "completely",
    "c": "completely"
  },
  "q83": {
    "q": "занепокоєння",
    "a1": "relaxation",
    "a2": "anxiety",
    "a3": "satisfaction",
    "a4": "happiness",
    "c": "anxiety"
  },
  "q84": {
    "q": "збивати з пантелику",
    "a1": "to upset",
    "a2": "to frighten",
    "a3": "to surprise",
    "a4": "to confuse",
    "c": "to confuse"
  },
  "q85": {
    "q": "розглянути",
    "a1": "to argue",
    "a2": "to review",
    "a3": "to discuss",
    "a4": "to reject",
    "c": "to review"
  },
  "q86": {
    "q": "розмова",
    "a1": "conversation",
    "a2": "quarrel",
    "a3": "argument",
    "a4": "debate",
    "c": "conversation"
  },
  "q87": {
    "q": "прохолодно",
    "a1": "cool",
    "a2": "cold",
    "a3": "hot",
    "a4": "warm",
    "c": "cool"
  },
  "q88": {
    "q": "куточок",
    "a1": "angle",
    "a2": "edge",
    "a3": "corner",
    "a4": "side",
    "c": "corner"
  },
  "q89": {
    "q": "диван",
    "a1": "sofa",
    "a2": "chair",
    "a3": "bed",
    "a4": "table",
    "c": "sofa"
  },
  "q90": {
    "q": "міг би",
    "a1": "may be",
    "a2": "should be",
    "a3": "might be",
    "a4": "could be",
    "c": "might be"
  },
  "q91": {
    "q": "не міг",
    "a1": "should not",
    "a2": "would not",
    "a3": "could not",
    "a4": "might not",
    "c": "could not"
  },
  "q92": {
    "q": "лічильник",
    "a1": "clock",
    "a2": "counter",
    "a3": "thermometer",
    "a4": "compass",
    "c": "counter"
  },
  "q93": {
    "q": "пара",
    "a1": "pair",
    "a2": "group",
    "a3": "couple",
    "a4": "team",
    "c": "pair"
  },
  "q94": {
    "q": "курс",
    "a1": "class",
    "a2": "course",
    "a3": "lesson",
    "a4": "lecture",
    "c": "course"
  },
  "q95": {
    "q": "обкладинка",
    "a1": "chapter",
    "a2": "index",
    "a3": "cover",
    "a4": "title",
    "c": "cover"
  },
  "q96": {
    "q": "тріщина",
    "a1": "dent",
    "a2": "gap",
    "a3": "crack",
    "a4": "hole",
    "c": "crack"
  },
  "q97": {
    "q": "божевільний",
    "a1": "sad",
    "a2": "angry",
    "a3": "crazy",
    "a4": "happy",
    "c": "crazy"
  },
  "q98": {
    "q": "хрест",
    "a1": "circle",
    "a2": "triangle",
    "a3": "cross",
    "a4": "square",
    "c": "cross"
  },
  "q99": {
    "q": "натовп",
    "a1": "audience",
    "a2": "group",
    "a3": "team",
    "a4": "crowd",
    "c": "crowd"
  },
  "q100": {
    "q": "милий",
    "a1": "cute",
    "a2": "nice",
    "a3": "kind",
    "a4": "lovely",
    "c": "lovely"
  }
}
